bulk_manager_django/BulkManager.py
bulk_manager_django/__init__.py
bulk_manager_django-0.1.2.dist-info/LICENSE
bulk_manager_django-0.1.2.dist-info/WHEEL
bulk_manager_django-0.1.2.dist-info/METADATA
bulk_manager_django-0.1.2.dist-info/RECORD
