Metadata-Version: 2.1
Name: bulk-manager-django
Version: 0.1.2
Summary: Easier management of the bulk create/update/delete for Django
Home-page: https://github.com/roodrepo/bulk_manager_django
License: MIT
Keywords: bulk create,bulk update,bulk delete,django
Author: Rood Repo
Author-email: roodrepo@gmail.com
Requires-Python: >=3.8,<4.0
Classifier: Framework :: Django :: 3
Classifier: Framework :: Django :: 4
Classifier: Intended Audience :: Developers
Classifier: License :: OSI Approved :: MIT License
Classifier: Operating System :: OS Independent
Classifier: Programming Language :: Python :: 3
Classifier: Programming Language :: Python :: 3.10
Classifier: Programming Language :: Python :: 3.8
Classifier: Programming Language :: Python :: 3.9
Classifier: Topic :: Software Development :: Libraries :: Python Modules
Requires-Dist: Django (>=3)
Requires-Dist: default-mutable (>=0.1.0,<0.2.0)
Project-URL: Repository, https://github.com/roodrepo/bulk_manager_django
